<ns0:test-suite xmlns:ns0="urn:model.allure.qatools.yandex.ru" start="1569243941417" stop="1569244039873">
  <name>testcases</name>
  <labels/>
  <test-cases>
    <test-case start="1569243941417" status="passed" stop="1569243958402">
      <name>test_about.TestAbout.test_mobile_info</name>
      <attachments/>
      <labels>
        <label name="severity" value="normal"/>
        <label name="thread" value="13440-MainThread"/>
        <label name="host" value="DESKTOP-QCTRQ3R"/>
        <label name="framework" value="pytest"/>
        <label name="language" value="cpython3"/>
      </labels>
      <steps/>
    </test-case>
    <test-case start="1569243959619" status="passed" stop="1569243977322">
      <name>test_display.TestDisplay.test_mobile_search[\u7f51\u7edc]</name>
      <attachments>
        <attachment source="3e60a19d-0cf1-4b2d-a038-c7ad8d663f3c-attachment.txt" title="描述" type="text/plain"/>
        <attachment source="cca29d62-8375-4761-9ff7-99eb3e73b6e5-attachment.txt" title="描述" type="text/plain"/>
        <attachment source="86a269c4-8675-4c15-8235-01c97eae88f7-attachment.txt" title="描述" type="text/plain"/>
      </attachments>
      <labels>
        <label name="testId" value="测试搜索功能"/>
        <label name="feature" value="测试用例：搜索"/>
        <label name="severity" value="normal"/>
        <label name="thread" value="13440-MainThread"/>
        <label name="host" value="DESKTOP-QCTRQ3R"/>
        <label name="framework" value="pytest"/>
        <label name="language" value="cpython3"/>
      </labels>
      <steps/>
    </test-case>
    <test-case start="1569243978591" status="passed" stop="1569243991829">
      <name>test_network.TestNetwork.test_mobile_network_2g</name>
      <attachments/>
      <labels>
        <label name="severity" value="normal"/>
        <label name="thread" value="13440-MainThread"/>
        <label name="host" value="DESKTOP-QCTRQ3R"/>
        <label name="framework" value="pytest"/>
        <label name="language" value="cpython3"/>
      </labels>
      <steps/>
    </test-case>
    <test-case start="1569243993055" status="passed" stop="1569244005993">
      <name>test_network.TestNetwork.test_mobile_network_3g</name>
      <attachments/>
      <labels>
        <label name="severity" value="normal"/>
        <label name="thread" value="13440-MainThread"/>
        <label name="host" value="DESKTOP-QCTRQ3R"/>
        <label name="framework" value="pytest"/>
        <label name="language" value="cpython3"/>
      </labels>
      <steps/>
    </test-case>
    <test-case start="1569244007259" status="passed" stop="1569244023040">
      <name>test_search.TestSearch.test_search[1]</name>
      <attachments/>
      <labels>
        <label name="severity" value="normal"/>
        <label name="thread" value="13440-MainThread"/>
        <label name="host" value="DESKTOP-QCTRQ3R"/>
        <label name="framework" value="pytest"/>
        <label name="language" value="cpython3"/>
      </labels>
      <steps/>
    </test-case>
    <test-case start="1569244024225" status="passed" stop="1569244039873">
      <name>test_search.TestSearch.test_search[2]</name>
      <attachments/>
      <labels>
        <label name="severity" value="normal"/>
        <label name="thread" value="13440-MainThread"/>
        <label name="host" value="DESKTOP-QCTRQ3R"/>
        <label name="framework" value="pytest"/>
        <label name="language" value="cpython3"/>
      </labels>
      <steps/>
    </test-case>
  </test-cases>
</ns0:test-suite>
